[
    {
        "comment_id": "C001",
        "key_moment_id": "KM040",
        "game_id": "G008",
        "transcript_id": "T040",
        "uploaded_by": "uid010",
        "comment": "Coach, what can I do next time?",
        "created_at": "2025-11-01T17:23:20Z"
    },
    {
        "comment_id": "C002",
        "key_moment_id": "KM017",
        "game_id": "G004",
        "transcript_id": "T017",
        "uploaded_by": "uid004",
        "comment": "Patrick, take the time to look at this key moment.",
        "created_at": "2025-11-07T06:23:39Z"
    },
    {
        "comment_id": "C003",
        "key_moment_id": "KM023",
        "game_id": "G005",
        "transcript_id": "T023",
        "uploaded_by": "uid006",
        "comment": "Coach, where should I aim to shoot next time?",
        "created_at": "2025-11-18T15:02:00Z"
    },
    {
        "comment_id": "C004",
        "key_moment_id": "KM031",
        "game_id": "G007",
        "transcript_id": "T031",
        "uploaded_by": "uid009",
        "comment": "I noticed I was not well positioned. Coach, where can I be next time to help with the attack when it's a corner kick?",
        "created_at": "2025-11-09T09:43:10Z"
    },
    {
        "comment_id": "C005",
        "key_moment_id": "T049",
        "game_id": "G010",
        "transcript_id": "T049",
        "uploaded_by": "uid001",
        "comment": "Mason make sure to look at this key moment as it happens often.",
        "created_at": "2025-10-19T19:40:00Z"
    }
]
